Metadata-Version: 2.1
Name: ratebypass
Version: 1.0
Summary: Ai Solver
Home-page: UNKNOWN
Author: helper
License: MIT
Keywords: style
Platform: UNKNOWN
Classifier: Development Status :: 5 - Production/Stable
